oss_vectors/__init__.py
oss_vectors/__version__.py
oss_vectors/cli.py
oss_vectors/commands/__init__.py
oss_vectors/commands/embed_put.py
oss_vectors/commands/embed_query.py
oss_vectors/core/__init__.py
oss_vectors/core/services.py
oss_vectors/core/streaming_batch_orchestrator.py
oss_vectors/core/unified_processor.py
oss_vectors/utils/__init__.py
oss_vectors/utils/config.py
oss_vectors/utils/models.py
oss_vectors/utils/multimodal_helpers.py
oss_vectors_embed_cli-0.1.0.dist-info/LICENSE
oss_vectors_embed_cli-0.1.0.dist-info/METADATA
oss_vectors_embed_cli-0.1.0.dist-info/WHEEL
oss_vectors_embed_cli-0.1.0.dist-info/entry_points.txt
oss_vectors_embed_cli-0.1.0.dist-info/top_level.txt
oss_vectors_embed_cli-0.1.0.dist-info/RECORD
