Metadata-Version: 2.1
Name: oss-vectors-embed-cli
Version: 0.1.0
Summary: Standalone CLI for OSS Vector operations with DashScope embeddings
Home-page: https://github.com/aliyun/oss-vectors-embed-cli
Author: fx
Author-email: 
Maintainer: fx
Maintainer-email: 
Project-URL: Bug Reports, https://github.com/aliyun/oss-vectors-embed-cli/issues
Project-URL: Source, https://github.com/aliyun/oss-vectors-embed-cli
Project-URL: Documentation, https://github.com/aliyun/oss-vectors-embed-cli#readme
Project-URL: Homepage, https://github.com/aliyun/oss-vectors-embed-cli
Keywords: oss,vectors,embeddings,dashscope,cli,machine-learning,ai
Classifier: Development Status :: 4 - Beta
Classifier: Intended Audience :: Developers
Classifier: Intended Audience :: System Administrators
Classifier: License :: OSI Approved :: Apache Software License
Classifier: Operating System :: OS Independent
Classifier: Programming Language :: Python :: 3
Classifier: Programming Language :: Python :: 3.9
Classifier: Programming Language :: Python :: 3.10
Classifier: Programming Language :: Python :: 3.11
Classifier: Programming Language :: Python :: 3.12
Classifier: Topic :: Software Development :: Libraries :: Python Modules
Classifier: Topic :: System :: Systems Administration
Classifier: Topic :: Utilities
Classifier: Topic :: Scientific/Engineering :: Artificial Intelligence
Classifier: Environment :: Console
Requires-Python: >=3.9
License-File: LICENSE
Requires-Dist: alibabacloud-oss-v2 (>=1.2.1)
Requires-Dist: click (>=8.0.0)
Requires-Dist: dashscope (>=1.25.1)
Requires-Dist: pydantic (>=1.10.0)
Requires-Dist: rich (>=12.0.0)
